{
    "title": "Getting started with Redpanda in K8s",
    "description": "Install Redpanda via helm chart",
    "details": {
      "intro": {
        "text": "intro.md"
      },
      "steps": [
        {
          "title": "Deploy a Redpanda Cluster",
          "text": "step1.md"
        },
        {
          "title": "Create topic, produce and consume events ",
          "text": "step2.md"
        },
        {
          "title": "Access Redpanda brokers, the Networks",
          "text": "step3.md"
        },
        {
          "title": "Deploy a python event consumer",
          "text": "step4.md"
        }
      ]
    },
    "backend": {
      "imageid": "kubernetes-kubeadm-2nodes"
    }
}
  